Workbook
Name l_scenario: 'Scenario sheet'!$B$7:$B$9
Name S_scenario: 'Scenario sheet'!$D$7

Sheet Model
B2: Geregu PLC
B3: Financial Forecast 2026- 2030
E4: 2024 | F4: 2025 | G4: =F4+1 -> 2026 | H4: =G4+1 -> 2027 | I4: =H4+1 -> 2028 | J4: =I4+1 -> 2029 | K4: =J4+1 -> 2030
B6: INCOME STATEMENT
B8: Revenue | E8: 137126532 | F8: 184935803 | G8: ='Assumption sheet'!F55 -> 2.2397997e+08 | H8: ='Assumption sheet'!G55 -> 2.5009535e+08 | I8: ='Assumption sheet'!H55 -> 2.7104135e+08 | J8: ='Assumption sheet'!I55 -> 2.9257093e+08 | K8: ='Assumption sheet'!J55 -> 3.146841e+08
B9: Cost of Sales | E9: -69865917 | F9: -100416543 | G9: =-'Assumption sheet'!F60 -> -1.2704092e+08 | H9: =-'Assumption sheet'!G60 -> -1.4284028e+08 | I9: =-'Assumption sheet'!H60 -> -1.5576134e+08 | J9: =-'Assumption sheet'!I60 -> -1.6908872e+08 | K9: =-'Assumption sheet'!J60 -> -1.828235e+08
B10: Gross Profit | E10: =SUM(E8:E9) -> 67260615 | F10: =SUM(F8:F9) -> 84519260 | G10: =SUM(G8:G9) -> 96939048 | H10: =SUM(H8:H9) -> 1.0725507e+08 | I10: =SUM(I8:I9) -> 1.1528001e+08 | J10: =SUM(J8:J9) -> 1.2348221e+08 | K10: =SUM(K8:K9) -> 1.318606e+08
B11: Other Income / (Loss) | E11: -583766 | F11: 1804896 | G11: 0 | H11: 0 | I11: 0 | J11: 0 | K11: 0
B12: SG&A Expenses | E12: -9354039 | F12: -17414424 | G12: =F12*(1+'Scenario sheet'!E12) -> -20549020 | H12: =G12*(1+'Scenario sheet'!F12) -> -23631373 | I12: =H12*(1+'Scenario sheet'!G12) -> -26467138 | J12: =I12*(1+'Scenario sheet'!H12) -> -29113852 | K12: =J12*(1+'Scenario sheet'!I12) -> -31879668
B13: Impairment Charge on Financial Assets | E13: -9401952 | F13: -10046707 | G13: =F13 -> -10046707 | H13: =G13 -> -10046707 | I13: =H13 -> -10046707 | J13: =I13 -> -10046707 | K13: =J13 -> -10046707
B14: EBITDA | E14: =SUM(E10:E13) -> 47920858 | F14: =SUM(F10:F13) -> 58863025 | G14: =SUM(G10:G13) -> 66343321 | H14: =SUM(H10:H13) -> 73576989 | I14: =SUM(I10:I13) -> 78766160 | J14: =SUM(J10:J13) -> 84321649 | K14: =SUM(K10:K13) -> 89934226
B15: Total Depreciation & Amortization (D&A) | E15: -4968135 | F15: -10713581 | G15: ='Assumption sheet'!F66 -> -9731551.6 | H15: ='Assumption sheet'!G66 -> -8827196.1 | I15: ='Assumption sheet'!H66 -> -8107690.8 | J15: ='Assumption sheet'!I66 -> -7583393.3 | K15: ='Assumption sheet'!J66 -> -7344766.8
B16: Operating Profit (EBIT) | E16: =SUM(E14:E15) -> 42952723 | F16: =SUM(F14:F15) -> 48149444 | G16: =SUM(G14:G15) -> 56611769 | H16: =SUM(H14:H15) -> 64749793 | I16: =SUM(I14:I15) -> 70658470 | J16: =SUM(J14:J15) -> 76738256 | K16: =SUM(K14:K15) -> 82589459
B17: Finance Income | E17: 8540399 | F17: 6425133 | G17: =15%*(AVERAGE(F36:G36)) -> 2426003.6 | H17: =15%*(AVERAGE(G36:H36)) -> 75000 | I17: =15%*(AVERAGE(H36:I36)) -> 239671.03 | J17: =15%*(AVERAGE(I36:J36)) -> 239671.03 | K17: =15%*(AVERAGE(J36:K36)) -> 166175.19
B18: Finance Cost | E18: -10227034 | F18: -12589544 | G18: =-'Assumption sheet'!F126 -> -14956552 | H18: =-'Assumption sheet'!G126 -> -16192793 | I18: =-'Assumption sheet'!H126 -> -15897467 | J18: =-'Assumption sheet'!I126 -> -13932953 | K18: =-'Assumption sheet'!J126 -> -11354315
B19: Profit Before Income Tax (PBT) | E19: =SUM(E16:E18) -> 41266088 | F19: =SUM(F16:F18) -> 41985033 | G19: =SUM(G16:G18) -> 44081221 | H19: =SUM(H16:H18) -> 48632000 | I19: =SUM(I16:I18) -> 55000673 | J19: =SUM(J16:J18) -> 63044973 | K19: =SUM(K16:K18) -> 71401320
B20: Income Tax Expense | E20: -13841019 | F20: -14734530 | G20: =-'Assumption sheet'!F91 -> -14387836 | H20: =-'Assumption sheet'!G91 -> -16230334 | I20: =-'Assumption sheet'!H91 -> -18472341 | J20: =-'Assumption sheet'!I91 -> -21275199 | K20: =-'Assumption sheet'!J91 -> -24259957
B21: Profit for the Year (Net Income) | E21: =SUM(E19:E20) -> 27425069 | F21: =SUM(F19:F20) -> 27250503 | G21: =SUM(G19:G20) -> 29693385 | H21: =SUM(H19:H20) -> 32401666 | I21: =SUM(I19:I20) -> 36528332 | J21: =SUM(J19:J20) -> 41769775 | K21: =SUM(K19:K20) -> 47141363
B23: BALANCE SHEET
B25: ASSETS
B26: Non-Current Assets
B27: Property, Plant and Equipment | E27: 72657733 | F27: 63050211 | G27: ='Assumption sheet'!F67 -> 56972259 | H27: ='Assumption sheet'!G67 -> 51896493 | I27: ='Assumption sheet'!H67 -> 48098360 | J27: ='Assumption sheet'!I67 -> 45430158 | K27: ='Assumption sheet'!J67 -> 45155300
B28: Intangible Assets | E28: 29 | F28: 0 | G28: 0 | H28: 0 | I28: 0 | J28: 0 | K28: 0
B29: Defined Benefit Plan Asset | E29: 11967 | F29: 50272 | G29: =F29 -> 50272 | H29: =G29 -> 50272 | I29: =H29 -> 50272 | J29: =I29 -> 50272 | K29: =J29 -> 50272
B30: Total Non-Current Assets | E30: =SUM(E27:E29) -> 72669729 | F30: =SUM(F27:F29) -> 63100483 | G30: =SUM(G27:G29) -> 57022531 | H30: =SUM(H27:H29) -> 51946765 | I30: =SUM(I27:I29) -> 48148632 | J30: =SUM(J27:J29) -> 45480430 | K30: =SUM(K27:K29) -> 45205572
B32: Current Assets
B33: Inventories | E33: 623675 | F33: 1314923 | G33: ='Assumption sheet'!F72 -> 1398811.1 | H33: ='Assumption sheet'!G72 -> 1721610.9 | I33: ='Assumption sheet'!H72 -> 1796194 | J33: ='Assumption sheet'!I72 -> 1993928.5 | K33: ='Assumption sheet'!J72 -> 2132079.3
B34: Trade and Other Receivables | E34: 121820410 | F34: 201108440 | G34: ='Assumption sheet'!F77 -> 2.2127312e+08 | H34: ='Assumption sheet'!G77 -> 2.5951954e+08 | I34: ='Assumption sheet'!H77 -> 2.745103e+08 | J34: ='Assumption sheet'!I77 -> 2.9995557e+08 | K34: ='Assumption sheet'!J77 -> 3.2066924e+08
B35: Other Current Assets | E35: 8420962 | F35: 7634826 | G35: =F35 -> 7634826 | H35: =G35 -> 7634826 | I35: =H35 -> 7634826 | J35: =I35 -> 7634826 | K35: =J35 -> 7634826
B36: Cash and Cash Equivalents | E36: 39935627 | F36: 31846715 | G36: =G90 -> 500000 | H36: =H90 -> 500000 | I36: =I90 -> 2695613.7 | J36: =J90 -> 500000 | K36: =K90 -> 1715669.2
B37: Total Current Assets | E37: =SUM(E33:E36) -> 170800674 | F37: =SUM(F33:F36) -> 241904904 | G37: =SUM(G33:G36) -> 2.3080676e+08 | H37: =SUM(H33:H36) -> 2.6937598e+08 | I37: =SUM(I33:I36) -> 2.8663693e+08 | J37: =SUM(J33:J36) -> 3.1008432e+08 | K37: =SUM(K33:K36) -> 3.3215182e+08
B38: TOTAL ASSETS | E38: =E37+E30 -> 243470403 | F38: =F37+F30 -> 305005387 | G38: =G37+G30 -> 2.8782929e+08 | H38: =H37+H30 -> 3.2132274e+08 | I38: =I37+I30 -> 3.3478556e+08 | J38: =J37+J30 -> 3.5556475e+08 | K38: =K37+K30 -> 3.7735739e+08
B40: EQUITY AND LIABILITIES
B41: Equity
B42: Share Capital | E42: 1250000 | F42: 1250000 | G42: =F42 -> 1250000 | H42: =G42 -> 1250000 | I42: =H42 -> 1250000 | J42: =I42 -> 1250000 | K42: =J42 -> 1250000
B43: Retained Earnings | E43: 51344328 | F43: 57344831 | G43: =F43+(25%*G21) -> 64768177 | H43: =G43+(25%*H21) -> 72868594 | I43: =H43+(25%*I21) -> 82000677 | J43: =I43+(25%*J21) -> 92443121 | K43: =J43+(25%*K21) -> 1.0422846e+08
B44: Actuarial Reserves | E44: -29408 | F44: 33169 | G44: =F44 -> 33169 | H44: =G44 -> 33169 | I44: =H44 -> 33169 | J44: =I44 -> 33169 | K44: =J44 -> 33169
B45: Total Equity | E45: =SUM(E42:E44) -> 52564920 | F45: =SUM(F42:F44) -> 58628000 | G45: =SUM(G42:G44) -> 66051346 | H45: =SUM(H42:H44) -> 74151763 | I45: =SUM(I42:I44) -> 83283846 | J45: =SUM(J42:J44) -> 93726290 | K45: =SUM(K42:K44) -> 1.0551163e+08
B47: Non-Current Liabilities
B48: Deferred Tax Liabilities | E48: 6979747 | F48: 4018115 | G48: ='Assumption sheet'!F96 -> 3418335.5 | H48: ='Assumption sheet'!G96 -> 3113789.6 | I48: ='Assumption sheet'!H96 -> 2885901.6 | J48: ='Assumption sheet'!I96 -> 2725809.5 | K48: ='Assumption sheet'!J96 -> 2709318
B49: Borrowings (Non-Current) | E49: 8483200 | F49: 4013538 | G49: =F49-'Assumption sheet'!F37 -> 3210830.4 | H49: =G49-'Assumption sheet'!G37 -> 2408122.8 | I49: =H49-'Assumption sheet'!H37 -> 1605415.2 | J49: =I49-'Assumption sheet'!I37 -> 802707.6 | K49: =J49-'Assumption sheet'!J37 -> 0
B50: Bond Payable (Non-Current) | E50: 32068000 | F50: 24180959 | G50: ='Assumption sheet'!F103 -> 19344767 | H50: ='Assumption sheet'!G103 -> 14508575 | I50: ='Assumption sheet'!H103 -> 9672383.6 | J50: ='Assumption sheet'!I103 -> 4836191.8 | K50: ='Assumption sheet'!J103 -> 0
B51: Total Non-Current Liabilities | E51: =SUM(E48:E50) -> 47530947 | F51: =SUM(F48:F50) -> 32212612 | G51: =SUM(G48:G50) -> 25973933 | H51: =SUM(H48:H50) -> 20030488 | I51: =SUM(I48:I50) -> 14163700 | J51: =SUM(J48:J50) -> 8364708.9 | K51: =SUM(K48:K50) -> 2709318
B53: Current Liabilities
B54: Trade and Other Payables | E54: 98135076 | F54: 136855640 | G54: ='Assumption sheet'!F82 -> 1.2763042e+08 | H54: ='Assumption sheet'!G82 -> 1.424209e+08 | I54: ='Assumption sheet'!H82 -> 1.5589407e+08 | J54: ='Assumption sheet'!I82 -> 1.6891255e+08 | K54: ='Assumption sheet'!J82 -> 1.8280615e+08
B55: Tax Payable | E55: 19970405 | F55: 37416567 | G55: =-G20 -> 14387836 | H55: =-H20 -> 16230334 | I55: =-I20 -> 18472341 | J55: =-J20 -> 21275199 | K55: =-K20 -> 24259957
B56: Borrowings (Current) | E56: 14682950 | F56: 29926449 | G56: =G108 -> 47141674 | H56: =H108 -> 65167214 | I56: =I108 -> 62971600 | J56: =J108 -> 63286006 | K56: =K108 -> 62070337
B57: Bond Payable (Current) | E57: 10586125 | F57: 9966119 | G57: ='Assumption sheet'!F110 -> 6644079.3 | H57: ='Assumption sheet'!G110 -> 3322039.7 | I57: ='Assumption sheet'!H110 -> -9.3132257e-09 | J57: ='Assumption sheet'!I110 -> -9.3132257e-09 | K57: ='Assumption sheet'!J110 -> -9.3132257e-09
B58: Total Current Liabilities | E58: =SUM(E54:E57) -> 143374556 | F58: =SUM(F54:F57) -> 214164775 | G58: =SUM(G54:G57) -> 1.9580401e+08 | H58: =SUM(H54:H57) -> 2.2714049e+08 | I58: =SUM(I54:I57) -> 2.3733801e+08 | J58: =SUM(J54:J57) -> 2.5347375e+08 | K58: =SUM(K54:K57) -> 2.6913644e+08
B59: TOTAL EQUITY AND LIABILITIES | E59: =E58+E51+E45 -> 243470423 | F59: =F58+F51+F45 -> 305005387 | G59: =G58+G51+G45 -> 2.8782929e+08 | H59: =H58+H51+H45 -> 3.2132274e+08 | I59: =I58+I51+I45 -> 3.3478556e+08 | J59: =J58+J51+J45 -> 3.5556475e+08 | K59: =K58+K51+K45 -> 3.7735739e+08
B62: Cash Flow Line Item
B63: 1. CASH FLOW FROM OPERATING ACTIVITIES
B64: Profit Before Tax (PBT) | C64: N'000 | G64: =G19 -> 44081221 | H64: =H19 -> 48632000 | I64: =I19 -> 55000673 | J64: =J19 -> 63044973 | K64: =K19 -> 71401320
B65: Adjustments for Non-Cash Items:
B66: + Depreciation & Amortization | C66: N'000 | G66: =-G15 -> 9731551.6 | H66: =-H15 -> 8827196.1 | I66: =-I15 -> 8107690.8 | J66: =-J15 -> 7583393.3 | K66: =-K15 -> 7344766.8
B67: +/- Deferred Tax Expense / (Benefit) | C67: N'000 | G67: ='Assumption sheet'!F95 -> -599779.46 | H67: ='Assumption sheet'!G95 -> -304545.96 | I67: ='Assumption sheet'!H95 -> -227888 | J67: ='Assumption sheet'!I95 -> -160092.1 | K67: ='Assumption sheet'!J95 -> -16491.501
B68: Changes in Operating Working Capital:
B69: +/- Change in Inventory | C69: N'000 | G69: =F33-G33 -> -83888.122 | H69: =G33-H33 -> -322799.77 | I69: =H33-I33 -> -74583.159 | J69: =I33-J33 -> -197734.45 | K69: =J33-K33 -> -138150.78
B70: +/- Change in Trade Receivables | C70: N'000 | G70: =F34-G34 -> -20164680 | H70: =G34-H34 -> -38246419 | I70: =H34-I34 -> -14990757 | J70: =I34-J34 -> -25445270 | K70: =J34-K34 -> -20713678
B71: +/- Change in Trade Payables | C71: N'000 | G71: =G54-F54 -> -9225220.3 | H71: =H54-G54 -> 14790482 | I71: =I54-H54 -> 13473171 | J71: =J54-I54 -> 13018474 | K71: =K54-J54 -> 13893601
B72: Finance cost | G72: 0 | H72: 0 | I72: 0 | J72: 0 | K72: 0
B73: Less: Cash Taxes Paid to FIRS | C73: N'000 | G73: =-F55 -> -37416567 | H73: =-G55 -> -14387836 | I73: =-H55 -> -16230334 | J73: =-I55 -> -18472341 | K73: =-J55 -> -21275199
B74: Net Cash Generated from Operating Activities (CFO) | C74: N'000 | G74: =SUM(G64:G73) -> -13677362 | H74: =SUM(H64:H73) -> 18988079 | I74: =SUM(I64:I73) -> 45057973 | J74: =SUM(J64:J73) -> 39371403 | K74: =SUM(K64:K73) -> 50496168
B76: 2. CASH FLOW FROM INVESTING ACTIVITIES
B77: Capital expenditure | C77: N'000 | G77: =-'Assumption sheet'!F65 -> -3653599.7 | H77: =-'Assumption sheet'!G65 -> -3751430.2 | I77: =-'Assumption sheet'!H65 -> -4309557.4 | J77: =-'Assumption sheet'!I65 -> -4915191.6 | K77: =-'Assumption sheet'!J65 -> -7069908.5
B78: Net Cash Used in Investing Activities (CFI) | C78: N'000 | G78: =SUM(G77) -> -3653599.7 | H78: =SUM(H77) -> -3751430.2 | I78: =SUM(I77) -> -4309557.4 | J78: =SUM(J77) -> -4915191.6 | K78: =SUM(K77) -> -7069908.5
B80: 3. CASH FLOW FROM FINANCING ACTIVITIES
B81: +/- Net Drawdown / (Repayment) of Revolver | C81: N'000 | G81: =G104-G107 -> 17215225 | H81: =H104-H107 -> 18025540 | I81: =I104-I107 -> -2195613.7 | J81: =J104-J107 -> 314405.51 | K81: =K104-K107 -> -1215669.2
B82: Less: LT Borrowings Principal Repayment | C82: N'000 | G82: =-'Assumption sheet'!F37 -> -802707.6 | H82: =-'Assumption sheet'!G37 -> -802707.6 | I82: =-'Assumption sheet'!H37 -> -802707.6 | J82: =-'Assumption sheet'!I37 -> -802707.6 | K82: =-'Assumption sheet'!J37 -> -802707.6
B83: Less: Annual Corporate Bond Repayment | C83: N'000 | G83: =-('Assumption sheet'!F42+'Assumption sheet'!F41) -> -8158231.5 | H83: =-('Assumption sheet'!G42+'Assumption sheet'!G41) -> -8158231.5 | I83: =-('Assumption sheet'!H42+'Assumption sheet'!H41) -> -8158231.5 | J83: =-('Assumption sheet'!I42+'Assumption sheet'!I41) -> -4836191.8 | K83: =-('Assumption sheet'!J42+'Assumption sheet'!J41) -> -4836191.8
B84: Less: Dividends Paid (75% Payout) | C84: N'000 | G84: =-G21*75% -> -22270039 | H84: =-H21*75% -> -24301250 | I84: =-I21*75% -> -27396249 | J84: =-J21*75% -> -31327331 | K84: =-K21*75% -> -35356022
B85: Net Cash Used in Financing Activities (CFF) | C85: N'000 | G85: =SUM(G81:G84) -> -14015753 | H85: =SUM(H81:H84) -> -15236648 | I85: =SUM(I81:I84) -> -38552802 | J85: =SUM(J81:J84) -> -36651825 | K85: =SUM(K81:K84) -> -42210591
B87: 4. NET CASH RECONCILIATION BLOCK
B88: Net Increase / (Decrease) in Cash & Equivalents | C88: N'000 | G88: =G74+G78+G85 -> -31346715 | H88: =H74+H78+H85 -> 0 | I88: =I74+I78+I85 -> 2195613.7 | J88: =J74+J78+J85 -> -2195613.7 | K88: =K74+K78+K85 -> 1215669.2
B89: Plus: Opening Cash & Equivalents Balance | C89: N'000 | G89: =F36 -> 31846715 | H89: =G36 -> 500000 | I89: =H36 -> 500000 | J89: =I36 -> 2695613.7 | K89: =J36 -> 500000
B90: Closing Cash & Equivalents Balance (BS) | C90: N'000 | G90: =SUM(G88:G89) -> 500000 | H90: =SUM(H88:H89) -> 500000 | I90: =SUM(I88:I89) -> 2695613.7 | J90: =SUM(J88:J89) -> 500000 | K90: =SUM(K88:K89) -> 1715669.2
B94: Revolver Calculation Block
B95: A. PRE-REVOLVER CASH POSITION
B96: Opening Cash Balance | C96: N'000 | G96: =G89 -> 31846715 | H96: =H89 -> 500000 | I96: =I89 -> 500000 | J96: =J89 -> 2695613.7 | K96: =K89 -> 500000
B97: + Net Operating Cash Flow (CFO) | C97: N'000 | G97: =G74 -> -13677362 | H97: =H74 -> 18988079 | I97: =I74 -> 45057973 | J97: =J74 -> 39371403 | K97: =K74 -> 50496168
B98: +/- Net Investing Cash Flow (CFI) | C98: N'000 | G98: =G78 -> -3653599.7 | H98: =H78 -> -3751430.2 | I98: =I78 -> -4309557.4 | J98: =J78 -> -4915191.6 | K98: =K78 -> -7069908.5
B99: − CFF Outflows (Excluding Revolver) | C99: N'000 | G99: =SUM(G82:G84) -> -31230978 | H99: =SUM(H82:H84) -> -33262189 | I99: =SUM(I82:I84) -> -36357188 | J99: =SUM(J82:J84) -> -36966230 | K99: =SUM(K82:K84) -> -40994921
B100: Preliminary Cash Before Revolver | C100: N'000 | G100: =SUM(G96:G99) -> -16715225 | H100: =SUM(H96:H99) -> -17525540 | I100: =SUM(I96:I99) -> 4891227.3 | J100: =SUM(J96:J99) -> 185594.49 | K100: =SUM(K96:K99) -> 2931338.5
B102: B. THE REVOLVER LIQUIDITY VALVE
B103: Target Minimum Cash Buffer | C103: N'000 | G103: 500000 | H103: 500000 | I103: 500000 | J103: 500000 | K103: 500000
B104: Required Revolver Drawdown | C104: N'000 | G104: =MAX(0,G103-G100) -> 17215225 | H104: =MAX(0,H103-H100) -> 18025540 | I104: =MAX(0,I103-I100) -> 0 | J104: =MAX(0,J103-J100) -> 314405.51 | K104: =MAX(0,K103-K100) -> 0
B105: Excess cash | G105: =MAX(0,G100-G103) -> 0 | H105: =MAX(0,H100-H103) -> 0 | I105: =MAX(0,I100-I103) -> 4391227.3 | J105: =MAX(0,J100-J103) -> 0 | K105: =MAX(0,K100-K103) -> 2431338.5
B106: Opening Revolver Outstanding Balance | C106: N'000 | G106: =F56 -> 29926449 | H106: =G56 -> 47141674 | I106: =H56 -> 65167214 | J106: =I56 -> 62971600 | K106: =J56 -> 63286006
B107: Revolver repayment | G107: =MIN(G106,G105*50%) -> 0 | H107: =MIN(H106,H105*50%) -> 0 | I107: =MIN(I106,I105*50%) -> 2195613.7 | J107: =MIN(J106,J105*50%) -> 0 | K107: =MIN(K106,K105*50%) -> 1215669.2
B108: Closing Revolver Balance (BS) | C108: N'000 | G108: =G106+G104-G107 -> 47141674 | H108: =H106+H104-H107 -> 65167214 | I108: =I106+I104-I107 -> 62971600 | J108: =J106+J104-J107 -> 63286006 | K108: =K106+K104-K107 -> 62070337

Sheet Assumption sheet
B2: Geregu PLC
B3: Financial Forecast 2026- 2030
B4: Assumption & calculations | D4: 2024 | E4: 2025 | F4: 2026 | G4: =F4+1 -> 2027 | H4: =G4+1 -> 2028 | I4: =H4+1 -> 2029 | J4: =I4+1 -> 2030
B6: ASSUMPTIONS & DRIVERS
B7: Macroeconomic Drivers
B8: USD / NGN Exchange Rate | C8: NGN/USD | F8: ='Scenario sheet'!E24 -> 1350 | G8: ='Scenario sheet'!F24 -> 1450 | H8: ='Scenario sheet'!G24 -> 1550 | I8: ='Scenario sheet'!H24 -> 1650 | J8: ='Scenario sheet'!I24 -> 1750
B9: Fully Loaded Gas Price (incl. Shrinkage & Levies) | C9: USD/Mscf | F9: ='Scenario sheet'!E18 -> 3.4 | G9: ='Scenario sheet'!F18 -> 3.45 | H9: ='Scenario sheet'!G18 -> 3.49 | I9: ='Scenario sheet'!H18 -> 3.53 | J9: ='Scenario sheet'!I18 -> 3.57
B11: Plant Operational Drivers
B12: Installed Capacity | C12: MW | F12: 435 | G12: 435 | H12: 435 | I12: 435 | J12: 435
B13: Plant Availability Factor | C13: % | F13: 0.88 | G13: 0.9 | H13: 0.9 | I13: 0.9 | J13: 0.9
B14: Plant Load Factor (PLF) / Dispatch Rate | C14: % | F14: 0.72 | G14: 0.75 | H14: =G14+0.01 -> 0.76 | I14: =H14+0.01 -> 0.77 | J14: =I14+0.01 -> 0.78
B15: Operating Hours | C15: Hours | F15: 8760 | G15: 8760 | H15: 8760 | I15: 8760 | J15: 8760
B16: Auxiliary Consumption Rate | C16: % | F16: 0.03 | G16: 0.03 | H16: 0.03 | I16: 0.03 | J16: 0.03
B17: Transmission Loss Factor (TLF) | C17: % | F17: 0.07 | G17: 0.07 | H17: 0.07 | I17: 0.07 | J17: 0.07
B18: Plant Heat Rate Efficiency | C18: Mscf/MWh | F18: 10.4 | G18: 10.3 | H18: 10.25 | I18: 10.2 | J18: 10.15
B20: Regulated Pricing Tariffs
B21: Wholesale Energy Tariff | C21: NGN/kWh | F21: 53 | G21: 56.5 | H21: 60 | I21: 63.5 | J21: 67
B22: Capacity Charge Rate | C22: USD/MW/Hour | F22: 20.5 | G22: 21 | H22: 21.5 | I22: 22 | J22: 22.5
B25: PP&E Assumptions & Drivers
B26: Routine Maintenance Capex | C26: % of Rev | F26: 0.01 | G26: =F26+0.5% -> 0.015 | H26: =G26+0.09% -> 0.0159 | I26: =H26+0.09% -> 0.0168 | J26: =I26+0.09% -> 0.0177
B27: Major Overhaul / Turnaround Spend | F27: 1413800 | G27: 0 | H27: 0 | I27: 0 | J27: 1500000
B28: Implied Depreciation Rate | C28: % | F28: 0.15 | G28: 0.15 | H28: 0.15 | I28: 0.15 | J28: 0.15
B30: Dividend pay out ratio | C30: % | F30: 0.75 | G30: 0.75 | H30: 0.75 | I30: 0.75 | J30: 0.75
B32: Capital allowance rate | C32: % of dep | F32: 1.05 | G32: 1.05 | H32: 1.05 | I32: 1.05 | J32: 1.05
B33: Blended Income Tax Rate | C33: % | F33: 0.34 | G33: 0.34 | H33: 0.34 | I33: 0.34 | J33: 0.34
B34: Deferred Tax Provision Rate | C34: % of PP&E | F34: 0.06 | G34: 0.06 | H34: 0.06 | I34: 0.06 | J34: 0.06
B35: Bank Borrowings Drivers
B36: Commercial Bank Borrowing Rate | C36: % | F36: 0.25 | G36: 0.22 | H36: 0.21 | I36: 0.2 | J36: 0.18
B37: LT Borrowings Principal Repayment | C37: N'000 | F37: 802707.6 | G37: 802707.6 | H37: 802707.6 | I37: 802707.6 | J37: 802707.6
B38: Corporate Bond Drivers
B39: Bond Coupon Rate (Fixed) | C39: % | F39: 0.147 | G39: 0.147 | H39: 0.147 | I39: 0.147 | J39: 0
B41: Bond Payable (Current Liability) | F41: 3322039.7 | G41: 3322039.7 | H41: 3322039.7 | I41: 0 | J41: 0
B42: Bond Payable (Non-Current Liability) | F42: 4836191.8 | G42: 4836191.8 | H42: 4836191.8 | I42: 4836191.8 | J42: 4836191.8
B47: Calculation
B49: Revenue calculation
B50: Gross power generation | F50: =F12*F15*F14 -> 2743632 | G50: =G12*G15*G14 -> 2857950 | H50: =H12*H15*H14 -> 2896056 | I50: =I12*I15*I14 -> 2934162 | J50: =J12*J15*J14 -> 2972268
B51: Net enegry sent out | F51: =F50*(1-F16) -> 2661323 | G51: =G50*(1-G16) -> 2772211.5 | H51: =H50*(1-H16) -> 2809174.3 | I51: =I50*(1-I16) -> 2846137.1 | J51: =J50*(1-J16) -> 2883100
B52: Net billable energy | F52: =F51*(1-F17) -> 2475030.4 | G52: =G51*(1-G17) -> 2578156.7 | H52: =H51*(1-H17) -> 2612532.1 | I52: =I51*(1-I17) -> 2646907.5 | J52: =J51*(1-J17) -> 2681283
B53: Energy sold revenue | F53: =F52*F21 -> 1.3117661e+08 | G53: =G52*G21 -> 1.4566585e+08 | H53: =H52*H21 -> 1.5675193e+08 | I53: =I52*I21 -> 1.6807863e+08 | J53: =J52*J21 -> 1.7964596e+08
B54: Capacity charge revenue | F54: =(F12*F15*F13*F22*F8)/1000 -> 92803352 | G54: =(G12*G15*G13*G22*G8)/1000 -> 104429493 | H54: =(H12*H15*H13*H22*H8)/1000 -> 1.1428942e+08 | I54: =(I12*I15*I13*I22*I8)/1000 -> 124492302 | J54: =(J12*J15*J13*J22*J8)/1000 -> 1.3503814e+08
B55: Total revenue | F55: =F53+F54 -> 2.2397997e+08 | G55: =G53+G54 -> 2.5009535e+08 | H55: =H53+H54 -> 2.7104135e+08 | I55: =I53+I54 -> 2.9257093e+08 | J55: =J53+J54 -> 3.146841e+08
B57: COS calculation
B58: Total gas volume | F58: =F51*F18 -> 27677760 | G58: =G51*G18 -> 28553778 | H58: =H51*H18 -> 28794037 | I58: =I51*I18 -> 29030599 | J58: =J51*J18 -> 29263465
B59: Fully loaded gas price | F59: =F9*F8 -> 4590 | G59: =G9*G8 -> 5002.5 | H59: =H9*H8 -> 5409.5 | I59: =I9*I8 -> 5824.5 | J59: =J9*J8 -> 6247.5
B60: Total COS | F60: =(F58*F59)/1000 -> 1.2704092e+08 | G60: =(G58*G59)/1000 -> 1.4284028e+08 | H60: =(H58*H59)/1000 -> 1.5576134e+08 | I60: =(I58*I59)/1000 -> 1.6908872e+08 | J60: =(J58*J59)/1000 -> 1.828235e+08
B63: PPE Schedule
B64: Opening Balance | F64: =Model!F27 -> 63050211 | G64: =F67 -> 56972259 | H64: =G67 -> 51896493 | I64: =H67 -> 48098360 | J64: =I67 -> 45430158
B65: Capital expenditure | F65: =F27+(F26*F55) -> 3653599.7 | G65: =G27+(G26*G55) -> 3751430.2 | H65: =H27+(H26*H55) -> 4309557.4 | I65: =I27+(I26*I55) -> 4915191.6 | J65: =J27+(J26*J55) -> 7069908.5
B66: Depreciation | F66: =-F28*(F64+(F65/2)) -> -9731551.6 | G66: =-G28*(G64+(G65/2)) -> -8827196.1 | H66: =-H28*(H64+(H65/2)) -> -8107690.8 | I66: =-I28*(I64+(I65/2)) -> -7583393.3 | J66: =-J28*(J64+(J65/2)) -> -7344766.8
B67: Ending balance | F67: =SUM(F64:F66) -> 56972259 | G67: =SUM(G64:G66) -> 51896493 | H67: =SUM(H64:H66) -> 48098360 | I67: =SUM(I64:I66) -> 45430158 | J67: =SUM(J64:J66) -> 45155300
B70: Inventory
B71: COS | D71: =-Model!E9 -> 69865917 | E71: =-Model!F9 -> 100416543 | F71: =-Model!G9 -> 1.2704092e+08 | G71: =-Model!H9 -> 1.4284028e+08 | H71: =-Model!I9 -> 1.5576134e+08 | I71: =-Model!J9 -> 1.6908872e+08 | J71: =-Model!K9 -> 1.828235e+08
B72: Inventory | D72: =Model!E33 -> 623675 | E72: =Model!F33 -> 1314923 | F72: =(F73/365)*F71 -> 1398811.1 | G72: =(G73/365)*G71 -> 1721610.9 | H72: =(H73/365)*H71 -> 1796194 | I72: =(I73/365)*I71 -> 1993928.5 | J72: =(J73/365)*J71 -> 2132079.3
B73: Days | D73: =(D72/D71)*365 -> 3.2582607 | E73: =(E72/E71)*365 -> 4.77956 | F73: =AVERAGE(D73:E73) -> 4.0189104 | G73: =AVERAGE(E73:F73) -> 4.3992352 | H73: =AVERAGE(F73:G73) -> 4.2090728 | I73: =AVERAGE(G73:H73) -> 4.304154 | J73: =AVERAGE(H73:I73) -> 4.2566134
B75: Receivable
B76: Revenue | D76: =Model!E8 -> 137126532 | E76: =Model!F8 -> 184935803 | F76: =Model!G8 -> 2.2397997e+08 | G76: =Model!H8 -> 2.5009535e+08 | H76: =Model!I8 -> 2.7104135e+08 | I76: =Model!J8 -> 2.9257093e+08 | J76: =Model!K8 -> 3.146841e+08
B77: Receivables | D77: =Model!E34 -> 121820410 | E77: =Model!F34 -> 201108440 | F77: =(F78/365)*F76 -> 2.2127312e+08 | G77: =(G78/365)*G76 -> 2.5951954e+08 | H77: =(H78/365)*H76 -> 2.745103e+08 | I77: =(I78/365)*I76 -> 2.9995557e+08 | J77: =(J78/365)*J76 -> 3.2066924e+08
B78: Days | D78: =(D77/D76)*365 -> 324.25854 | E78: =(E77/E76)*365 -> 396.91925 | F78: =AVERAGE(D78:E78) -> 360.5889 | G78: =AVERAGE(E78:F78) -> 378.75408 | H78: =AVERAGE(F78:G78) -> 369.67149 | I78: =AVERAGE(G78:H78) -> 374.21278 | J78: =AVERAGE(H78:I78) -> 371.94213
B80: Payables
B81: =B71 -> COS | D81: =-Model!E9 -> 69865917 | E81: =-Model!F9 -> 100416543 | F81: =-Model!G9 -> 1.2704092e+08 | G81: =-Model!H9 -> 1.4284028e+08 | H81: =-Model!I9 -> 1.5576134e+08 | I81: =-Model!J9 -> 1.6908872e+08 | J81: =-Model!K9 -> 1.828235e+08
B82: Payables | D82: =Model!E54 -> 98135076 | E82: =Model!F54 -> 136855640 | F82: =F83/365*F81 -> 1.2763042e+08 | G82: =G83/365*G81 -> 1.424209e+08 | H82: =H83/365*H81 -> 1.5589407e+08 | I82: =I83/365*I81 -> 1.6891255e+08 | J82: =J83/365*J81 -> 1.8280615e+08
B83: Days | D83: =(D82/D81)*265 -> 372.22434 | E83: =(E82/E81)*265 -> 361.16305 | F83: =AVERAGE(D83:E83) -> 366.6937 | G83: =AVERAGE(E83:F83) -> 363.92837 | H83: =AVERAGE(F83:G83) -> 365.31103 | I83: =AVERAGE(G83:H83) -> 364.6197 | J83: =AVERAGE(H83:I83) -> 364.96537
B87: Current Tax Schedule
B88: Profit Before Tax (PBT) | F88: =Model!G19 -> 44081221 | G88: =Model!H19 -> 48632000 | H88: =Model!I19 -> 55000673 | I88: =Model!J19 -> 63044973 | J88: =Model!K19 -> 71401320
B89: Company Income Tax Provision (30%) | F89: =F88*F33 -> 14987615 | G89: =G88*G33 -> 16534880 | H89: =H88*H33 -> 18700229 | I89: =I88*I33 -> 21435291 | J89: =J88*J33 -> 24276449
B90: Deffered tax lability | F90: =F95 -> -599779.46 | G90: =G95 -> -304545.96 | H90: =H95 -> -227888 | I90: =I95 -> -160092.1 | J90: =J95 -> -16491.501
B91: Total Current Tax Expense | F91: =F90+F89 -> 14387836 | G91: =G90+G89 -> 16230334 | H91: =H90+H89 -> 18472341 | I91: =I90+I89 -> 21275199 | J91: =J90+J89 -> 24259957
B93: Deferred tax iability
B94: Opening balance | F94: =Model!F48 -> 4018115 | G94: =F96 -> 3418335.5 | H94: =G96 -> 3113789.6 | I94: =H96 -> 2885901.6 | J94: =I96 -> 2725809.5
B95: Increase/decrease | F95: =F96-F94 -> -599779.46 | G95: =G96-G94 -> -304545.96 | H95: =H96-H94 -> -227888 | I95: =I96-I94 -> -160092.1 | J95: =J96-J94 -> -16491.501
B96: Closing balance | F96: =F67*F34 -> 3418335.5 | G96: =G67*G34 -> 3113789.6 | H96: =H67*H34 -> 2885901.6 | I96: =I67*I34 -> 2725809.5 | J96: =J67*J34 -> 2709318
B99: Borrowings
B100: Bond Payable (Non-Current)
B101: Opening balance | F101: =Model!F50 -> 24180959 | G101: =F103 -> 19344767 | H101: =G103 -> 14508575 | I101: =H103 -> 9672383.6 | J101: =I103 -> 4836191.8
B102: Repayment | F102: =-F42 -> -4836191.8 | G102: =-G42 -> -4836191.8 | H102: =-H42 -> -4836191.8 | I102: =-I42 -> -4836191.8 | J102: =-J42 -> -4836191.8
B103: Closing Balance | F103: =SUM(F101:F102) -> 19344767 | G103: =SUM(G101:G102) -> 14508575 | H103: =SUM(H101:H102) -> 9672383.6 | I103: =SUM(I101:I102) -> 4836191.8 | J103: =SUM(J101:J102) -> 0
B105: Interest expense | F105: =AVERAGE(F103,F101)*F39 -> 3199140.9 | G105: =AVERAGE(G103,G101)*G39 -> 2488220.7 | H105: =AVERAGE(H103,H101)*H39 -> 1777300.5 | I105: =AVERAGE(I103,I101)*I39 -> 1066380.3 | J105: =AVERAGE(J103,J101)*J39 -> 0
B107: Bond Payable (Current)
B108: Opening balance | F108: =Model!F57 -> 9966119 | G108: =Model!G57 -> 6644079.3 | H108: =Model!H57 -> 3322039.7 | I108: =Model!I57 -> -9.3132257e-09 | J108: =Model!J57 -> -9.3132257e-09
B109: Repayment | F109: =-F41 -> -3322039.7 | G109: =-G41 -> -3322039.7 | H109: =-H41 -> -3322039.7 | I109: =-I41 -> 0 | J109: =-J41 -> 0
B110: Closing Balance | F110: =SUM(F108:F109) -> 6644079.3 | G110: =SUM(G108:G109) -> 3322039.7 | H110: =SUM(H108:H109) -> -9.3132257e-09 | I110: =SUM(I108:I109) -> -9.3132257e-09 | J110: =SUM(J108:J109) -> -9.3132257e-09
B112: Interest expense | F112: =AVERAGE(F108,F110)*F39 -> 1220849.6 | G112: =AVERAGE(G108,G110)*G39 -> 732509.75 | H112: =AVERAGE(H108,H110)*H39 -> 244169.92 | I112: =AVERAGE(I108,I110)*I39 -> -1.3690442e-09 | J112: =AVERAGE(J108,J110)*J39 -> 0
B114: LT Borrowings
B115: Opening balance | F115: =Model!F49 -> 4013538 | G115: =F117 -> 3210830.4 | H115: =G117 -> 2408122.8 | I115: =H117 -> 1605415.2 | J115: =I117 -> 802707.6
B116: Repayment | F116: =-F37 -> -802707.6 | G116: =-G37 -> -802707.6 | H116: =-H37 -> -802707.6 | I116: =-I37 -> -802707.6 | J116: =-J37 -> -802707.6
B117: Closing Balance | F117: =SUM(F115:F116) -> 3210830.4 | G117: =SUM(G115:G116) -> 2408122.8 | H117: =SUM(H115:H116) -> 1605415.2 | I117: =SUM(I115:I116) -> 802707.6 | J117: =SUM(J115:J116) -> 0
B119: Interest expense | F119: =F36*AVERAGE(F115,F117) -> 903046.05 | G119: =G36*AVERAGE(G115,G117) -> 618084.85 | H119: =H36*AVERAGE(H115,H117) -> 421421.49 | I119: =I36*AVERAGE(I115,I117) -> 240812.28 | J119: =J36*AVERAGE(J115,J117) -> 72243.684
B121: Interest expense
B122: Non current bond | F122: =F105 -> 3199140.9 | G122: =G105 -> 2488220.7 | H122: =H105 -> 1777300.5 | I122: =I105 -> 1066380.3 | J122: =J105 -> 0
B123: =B107 -> Bond Payable (Current) | F123: =F112 -> 1220849.6 | G123: =G112 -> 732509.75 | H123: =H112 -> 244169.92 | I123: =I112 -> -1.3690442e-09 | J123: =J112 -> 0
B124: Interest on revolver | F124: =F36*(AVERAGE(Model!G106,Model!G108)) -> 9633515.4 | G124: =G36*(AVERAGE(Model!H106,Model!H108)) -> 12353978 | H124: =H36*(AVERAGE(Model!I106,Model!I108)) -> 13454576 | I124: =I36*(AVERAGE(Model!J106,Model!J108)) -> 12625761 | J124: =J36*(AVERAGE(Model!K106,Model!K108)) -> 11282071
B125: Interest on lt borrowings | F125: =F119 -> 903046.05 | G125: =G119 -> 618084.85 | H125: =H119 -> 421421.49 | I125: =I119 -> 240812.28 | J125: =J119 -> 72243.684
B126: Interest expense | F126: =SUM(F122:F125) -> 14956552 | G126: =SUM(G122:G125) -> 16192793 | H126: =SUM(H122:H125) -> 15897467 | I126: =SUM(I122:I125) -> 13932953 | J126: =SUM(J122:J125) -> 11354315

Sheet DCF
C2: Geregu PLC | F2: Key Outputs
C3: Discounted Cash Flow Valuation | F3: WACC | G3: =D38 -> 0.1549
F4: Terminal Growth Rate (g) | G4: =D41 -> 0.0947
F5: Enterprise Value | G5: =D73 -> 5.3125892e+08
C6: 1. COST OF CAPITAL | F6: Equity Value | G6: =D76 -> 4.9501857e+08
F7: Current market Price par share | G7: 917.4
C8: Nigeria Country Risk
C9: Nigeria Default Spread (adj. for equity market volatility) | D9: 0.0552
C10: Nigeria Country Risk Premium (CRP) | D10: 0.0841
C11: Nigeria Total Equity Risk Premium (= Mature Market ERP + Nigeria CRP) | D11: 0.1264
C12: Risk-Free Rate, NGN (= Rf US$ + Nigeria Default Spread) | D12: 0.0947
C14: Beta
C15: Power Industry Unlevered Beta (Global comparables) | D15: 0.43
C16: Geregu Total Interest-Bearing Debt (FY2025A, book value, N'000) | D16: 68087065
C17: Geregu Total Equity (FY2025A, book value, N'000) | D17: 58628000
C18: Debt / Equity (book value, FY2025A) | D18: =D17/D16 -> 0.86107398
C19: Marginal Tax Rate (linked to 3-statement model) | D19: ='Assumption sheet'!F33 -> 0.34
C20: Relevered Beta (= Unlevered β × [1 + (1−t) × D/E]) | D20: 0.76
C22: Cost of Equity
C23: Cost of Equity (Ke) = Rf,NGN + Relevered β × Nigeria Total ERP | D23: 0.1907
C26: 2025 Finance Cost (interest expense) | D26: 12589544
C27: 2024Total Interest-Bearing Debt | D27: 65820275
C28: 2025 Total Interest-Bearing Debt | D28: 68087065
C29: Average Total Debt (FY2024A–FY2025A) | D29: 66953670
C30: Pre-Tax Cost of Debt (Kd) = Finance Cost / Average Total Debt | D30: 0.188
C31: After-Tax Cost of Debt = Kd × (1 − t) | D31: 0.1241
C33: Capital Structure Weights (book value, FY2025A)
C34: Weight of Debt, D / (D+E) | D34: 0.5373
C35: Weight of Equity, E / (D+E) | D35: 0.4627
C37: WACC
C38: WACC = (E/V × Ke) + (D/V × Kd × (1−t)) | D38: 0.1549
C40: Terminal Growth Rate
C41: Terminal Growth Rate (g) — capped at Risk-Free Rate, NGN | D41: 0.0947
C44: 2. UNLEVERED FREE CASH FLOW (FCFF)
C46: Fiscal Year | E46: 2026 | F46: 2027 | G46: 2028 | H46: 2029 | I46: 2030
C47: EBIT (Operating Profit) | E47: =Model!G16 -> 56611769 | F47: =Model!H16 -> 64749793 | G47: =Model!I16 -> 70658470 | H47: =Model!J16 -> 76738256 | I47: =Model!K16 -> 82589459
C48: Tax Rate (linked to Assumption sheet) | E48: ='Assumption sheet'!F33 -> 0.34 | F48: ='Assumption sheet'!G33 -> 0.34 | G48: ='Assumption sheet'!H33 -> 0.34 | H48: ='Assumption sheet'!I33 -> 0.34 | I48: ='Assumption sheet'!J33 -> 0.34
C49: NOPAT = EBIT × (1 − Tax Rate) | E49: =E47*(1-E48) -> 37363768 | F49: =F47*(1-F48) -> 42734863 | G49: =G47*(1-G48) -> 46634590 | H49: =H47*(1-H48) -> 50647249 | I49: =I47*(1-I48) -> 54509043
C50: Depreciation & Amortization | E50: =-Model!G15 -> 9731551.6 | F50: =-Model!H15 -> 8827196.1 | G50: =-Model!I15 -> 8107690.8 | H50: =-Model!J15 -> 7583393.3 | I50: =-Model!K15 -> 7344766.8
C51: Capital Expenditure | E51: =-'Assumption sheet'!F65 -> -3653599.7 | F51: =-'Assumption sheet'!G65 -> -3751430.2 | G51: =-'Assumption sheet'!H65 -> -4309557.4 | H51: =-'Assumption sheet'!I65 -> -4915191.6 | I51: =-'Assumption sheet'!J65 -> -7069908.5
C52: Change in Net Working Capital | E52: =SUM(Model!G69:G71) -> -29473788 | F52: =SUM(Model!H69:H71) -> -23778736 | G52: =SUM(Model!I69:I71) -> -1592168.8 | H52: =SUM(Model!J69:J71) -> -12624531 | I52: =SUM(Model!K69:K71) -> -6958228
C53: Unlevered Free Cash Flow (FCFF) | E53: =SUM(E49:E52) -> 13967931 | F53: =SUM(F49:F52) -> 24031893 | G53: =SUM(G49:G52) -> 48840554 | H53: =SUM(H49:H52) -> 40690919 | I53: =SUM(I49:I52) -> 47825673
C55: 3. DISCOUNTING & TERMINAL VALUE
C57: Discount Period (n) | E57: 1 | F57: 2 | G57: 3 | H57: 4 | I57: 5
C58: Discount Factor = 1 / (1+WACC)^n | E58: =1/(1+$D$38)^E57 -> 0.86587583 | F58: =1/(1+$D$38)^F57 -> 0.74974096 | G58: =1/(1+$D$38)^G57 -> 0.64918258 | H58: =1/(1+$D$38)^H57 -> 0.56211151 | I58: =1/(1+$D$38)^I57 -> 0.48671877
C59: PV of FCFF | E59: =E53*E58 -> 12094494 | F59: =F53*F58 -> 18017695 | G59: =G53*G58 -> 31706437 | H59: =H53*H58 -> 22872834 | I59: =I53*I58 -> 23277653
C61: Sum of PV — Explicit Period (FY2026–FY2030) | D61: =SUM(E59:I59) -> 1.0796911e+08
C63: Terminal Value
C64: FCFF, FY2030 | D64: =I53 -> 47825673
C65: Terminal Value = FCFF2030 × (1+g) / (WACC − g) | D65: =(D64*(1+D41))/(D38-D41) -> 8.6968048e+08
C66: PV of Terminal Value = TV × Discount Factor, FY2030 | D66: =D65*I58 -> 4.2328981e+08
C67: Terminal Value as % of Enterprise Value
C69: Enterprise Value = Sum PV(FCFF) + PV(Terminal Value) | D69: =D66+D61 -> 5.3125892e+08
C71: 4. BRIDGE TO EQUITY VALUE PER SHARE
C73: Enterprise Value | D73: =D69 -> 5.3125892e+08
C74: Total Debt | D74: =-(Model!F49+Model!F50+Model!F56+Model!F57) -> -68087065
C75: Cash & Cash Equivalents | D75: =Model!F36 -> 31846715
C76: Equity Value | D76: =SUM(D73:D75) -> 4.9501857e+08
C78: Shares Outstanding | D78: 2509372139
C79: Value per Share | D79: =(D76/D78)*1000 -> 197.2679

Sheet Scenario sheet
B2: Geregu PLC
B3: Financial Forecast 2026- 2030
B4: Scenario sheet | E4: 2026 | F4: =E4+1 -> 2027 | G4: =F4+1 -> 2028 | H4: =G4+1 -> 2029 | I4: =H4+1 -> 2030
B7: Base Case | D7: 1
B8: Bull Case
B9: Bear Case
B11: Inflation
B12: Used in model | E12: {=INDEX(E13:E15,S_scenario)} -> 0.18 | F12: {=INDEX(F13:F15,S_scenario)} -> 0.15 | G12: {=INDEX(G13:G15,S_scenario)} -> 0.12 | H12: {=INDEX(H13:H15,S_scenario)} -> 0.1 | I12: {=INDEX(I13:I15,S_scenario)} -> 0.095
B13: Base Case | E13: 0.18 | F13: 0.15 | G13: 0.12 | H13: 0.1 | I13: 0.095
B14: Bull Case | E14: 0.14 | F14: 0.11 | G14: 0.09 | H14: 0.075 | I14: 0.06
B15: Bear Case | E15: 0.25 | F15: 0.22 | G15: 0.18 | H15: 0.16 | I15: 0.15
B17: Fully Loaded Gas Price Matrix
B18: Used in model | E18: {=INDEX(E19:E21,S_scenario)} -> 3.4 | F18: {=INDEX(F19:F21,S_scenario)} -> 3.45 | G18: {=INDEX(G19:G21,S_scenario)} -> 3.49 | H18: {=INDEX(H19:H21,S_scenario)} -> 3.53 | I18: {=INDEX(I19:I21,S_scenario)} -> 3.57
B19: Base Case | E19: 3.4 | F19: 3.45 | G19: 3.49 | H19: 3.53 | I19: 3.57
B20: Bull Case | E20: 3.35 | F20: 3.32 | G20: 3.3 | H20: 3.3 | I20: 3.3
B21: Bear Case | E21: 3.75 | F21: 3.85 | G21: 3.92 | H21: 4.05 | I21: 4.15
B23: USD / NGN Exchange Rate
B24: Used in model | E24: {=INDEX(E25:E27,S_scenario)} -> 1350 | F24: {=INDEX(F25:F27,S_scenario)} -> 1450 | G24: {=INDEX(G25:G27,S_scenario)} -> 1550 | H24: {=INDEX(H25:H27,S_scenario)} -> 1650 | I24: {=INDEX(I25:I27,S_scenario)} -> 1750
B25: Base Case | E25: 1350 | F25: 1450 | G25: 1550 | H25: 1650 | I25: 1750
B26: Bull Case | E26: 1200 | F26: 1250 | G26: 1300 | H26: 1350 | I26: 1400
B27: Bear Case | E27: 1650 | F27: 1800 | G27: 1950 | H27: 2100 | I27: 2200
